setup.py
imhotep/__init__.py
imhotep/app.py
imhotep/app_test.py
imhotep/diff_parser.py
imhotep/diff_parser_test.py
imhotep/errors.py
imhotep/http.py
imhotep/http_test.py
imhotep/integration_test.py
imhotep/main.py
imhotep/main_test.py
imhotep/repomanagers.py
imhotep/repomanagers_test.py
imhotep/reporters.py
imhotep/reporters_test.py
imhotep/repositories.py
imhotep/repositories_test.py
imhotep/shas.py
imhotep/shas_test.py
imhotep/testing_utils.py
imhotep/tools.py
imhotep/tools_test.py
imhotep/regression_tests/__init__.py
imhotep/regression_tests/test_25.py
penthu.egg-info/PKG-INFO
penthu.egg-info/SOURCES.txt
penthu.egg-info/dependency_links.txt
penthu.egg-info/entry_points.txt
penthu.egg-info/requires.txt
penthu.egg-info/top_level.txt