Metadata-Version: 1.0
Name: penthu
Version: 0.1.1
Summary: A tool to pipe linters into code review
Home-page: https://github.com/justinabrahms/imhotep
Author: Justin Abrahms
Author-email: justin@abrah.ms
License: MIT
Platform: UNKNOWN
